py_allrecipes/__init__.py
py_allrecipes/recipe.py
py_allrecipes/search.py
py_allrecipes-1.1.0.dist-info/METADATA
py_allrecipes-1.1.0.dist-info/WHEEL
py_allrecipes-1.1.0.dist-info/entry_points.txt
py_allrecipes-1.1.0.dist-info/licenses/LICENSE
py_allrecipes-1.1.0.dist-info/RECORD
