Metadata-Version: 2.4
Name: py-allrecipes
Version: 1.1.0
Summary: Python API to access the Allrecipes platform.
Author-email: Zachary Jones <zacharyj@orbical.dev>
License-File: LICENSE
Requires-Python: >=3.12
Requires-Dist: beautifulsoup4
Requires-Dist: requests
